ProjectHelper/__init__.py
ProjectHelper/main.py
ProjectHelper-0.0.1.dist-info/DESCRIPTION.rst
ProjectHelper-0.0.1.dist-info/METADATA
ProjectHelper-0.0.1.dist-info/RECORD
ProjectHelper-0.0.1.dist-info/WHEEL
ProjectHelper-0.0.1.dist-info/entry_points.txt
ProjectHelper-0.0.1.dist-info/metadata.json
ProjectHelper-0.0.1.dist-info/top_level.txt
