Metadata-Version: 2.0
Name: ProjectHelper
Version: 0.0.1
Summary: Project generator for software creating by the Python programming language
Home-page: https://github.com/setivolkylany/PythonUtils
Author: setivolkylany
Author-email: setivolkylany@gmail.com
License: GNU GPLv3
Keywords: python utils programming
Platform: UNKNOWN
Classifier: Development Status :: 1 - Planning
Classifier: Intended Audience :: Developers
Classifier: Topic :: Software Development
Classifier: License :: OSI Approved :: GNU General Public License v3 (GPLv3)
Classifier: Programming Language :: Python :: 3.4
Classifier: Programming Language :: Python :: 3.5
Requires-Dist: ipdb (>=0.10.0)
Requires-Dist: ipython (>=5.1.0)
Requires-Dist: factory-boy (>=2.7.0)
Requires-Dist: invoke (>=0.13.0)
Requires-Dist: Pillow (>=3.4.2)
Requires-Dist: python-dateutil (>=2.6.0)
Requires-Dist: Unipath (>=1.1)
Provides-Extra: dev
Provides-Extra: test
